ble_scanner/BLEScanner.py
ble_scanner/__init__.py
ble_scanner/cli.py
ble_scanner-1.0.7.dist-info/METADATA
ble_scanner-1.0.7.dist-info/WHEEL
ble_scanner-1.0.7.dist-info/top_level.txt
ble_scanner-1.0.7.dist-info/RECORD
