Metadata-Version: 2.1
Name: ble-scanner
Version: 1.0.7
Summary: BLE Beacon scanner
Home-page: https://github.com/oashaikh/ble-scanner
Author: Osama Ashaikh
Author-email: oashaikh@gmail.com
Keywords: pypi,BLE,python,scanner,beacon
Requires-Dist: bleak
